odoo8_addon_l10n_es_dua_sii-8.0.1.0.3-nspkg.pth
odoo_addons/l10n_es_dua_sii/README.rst
odoo_addons/l10n_es_dua_sii/__init__.py
odoo_addons/l10n_es_dua_sii/__openerp__.py
odoo_addons/l10n_es_dua_sii/i18n/bg.po
odoo_addons/l10n_es_dua_sii/i18n/ca.po
odoo_addons/l10n_es_dua_sii/i18n/cs.po
odoo_addons/l10n_es_dua_sii/i18n/en_US.po
odoo_addons/l10n_es_dua_sii/i18n/es.po
odoo_addons/l10n_es_dua_sii/i18n/es_CR.po
odoo_addons/l10n_es_dua_sii/i18n/fr.po
odoo_addons/l10n_es_dua_sii/i18n/gl.po
odoo_addons/l10n_es_dua_sii/i18n/hr.po
odoo_addons/l10n_es_dua_sii/i18n/l10n_es_dua_sii.pot
odoo_addons/l10n_es_dua_sii/i18n/nl.po
odoo_addons/l10n_es_dua_sii/i18n/pl.po
odoo_addons/l10n_es_dua_sii/i18n/pt.po
odoo_addons/l10n_es_dua_sii/i18n/pt_BR.po
odoo_addons/l10n_es_dua_sii/i18n/ru.po
odoo_addons/l10n_es_dua_sii/i18n/sl.po
odoo_addons/l10n_es_dua_sii/i18n/sv.po
odoo_addons/l10n_es_dua_sii/i18n/tr.po
odoo_addons/l10n_es_dua_sii/models/__init__.py
odoo_addons/l10n_es_dua_sii/models/account_invoice.py
odoo_addons/l10n_es_dua_sii/static/description/icon.png
odoo8_addon_l10n_es_dua_sii-8.0.1.0.3.dist-info/METADATA
odoo8_addon_l10n_es_dua_sii-8.0.1.0.3.dist-info/WHEEL
odoo8_addon_l10n_es_dua_sii-8.0.1.0.3.dist-info/namespace_packages.txt
odoo8_addon_l10n_es_dua_sii-8.0.1.0.3.dist-info/top_level.txt
odoo8_addon_l10n_es_dua_sii-8.0.1.0.3.dist-info/RECORD
